FAIRLinked/__init__.py
FAIRLinked/__main__.py
FAIRLinked/InterfaceMDS/__init__.py
FAIRLinked/InterfaceMDS/add_ontology_term.py
FAIRLinked/InterfaceMDS/convert_ttl_to_drawio.py
FAIRLinked/InterfaceMDS/domain_subdomain_viewer.py
FAIRLinked/InterfaceMDS/load_mds_ontology.py
FAIRLinked/InterfaceMDS/rdf_subject_extractor.py
FAIRLinked/InterfaceMDS/term_search_general.py
FAIRLinked/QBWorkflow/__init__.py
FAIRLinked/QBWorkflow/data_parser.py
FAIRLinked/QBWorkflow/data_template_generator.py
FAIRLinked/QBWorkflow/input_handler.py
FAIRLinked/QBWorkflow/mds_ontology_analyzer.py
FAIRLinked/QBWorkflow/namespace_parser.py
FAIRLinked/QBWorkflow/namespace_template_generator.py
FAIRLinked/QBWorkflow/rdf_data_cube_workflow.py
FAIRLinked/QBWorkflow/rdf_to_df.py
FAIRLinked/QBWorkflow/rdf_transformer.py
FAIRLinked/QBWorkflow/utility.py
FAIRLinked/RDFTableConversion/__init__.py
FAIRLinked/RDFTableConversion/csv_to_jsonld_mapper.py
FAIRLinked/RDFTableConversion/csv_to_jsonld_template_filler.py
FAIRLinked/RDFTableConversion/jsonld_batch_converter.py
FAIRLinked/cli/__init__.py
FAIRLinked/cli/__main__.py
FAIRLinked/helper_data/__init__.py
fairlinked-0.3.2.4.dist-info/licenses/LICENSE.txt
fairlinked-0.3.2.4.dist-info/METADATA
fairlinked-0.3.2.4.dist-info/WHEEL
fairlinked-0.3.2.4.dist-info/entry_points.txt
fairlinked-0.3.2.4.dist-info/top_level.txt
fairlinked-0.3.2.4.dist-info/RECORD
