Metadata-Version: 2.4
Name: FAIRLinked
Version: 0.3.2.4
Summary: Transform materials research data into FAIR-compliant RDF Data. Align your datasets with MDS-Onto and convert them into Linked Data, enhancing interoperability and reusability for seamless data integration. See the README or vignette for more information. This tool is used by the SDLE Research Center at Case Western Reserve University.
Author: Van D. Tran, Brandon Lee, Henry Dirks, Ritika Lamba, Balashanmuga Priyan Rajamohan, Gabriel Ponon, Quynh D. Tran, Ozan Dernek, Yinghui Wu, Erika I. Barcelos, Roger H. French, Laura S. Bruckman
Author-email: rxf131@case.edu
License: BSD-3-Clause
Project-URL: Documentation, https://fairlinked.readthedocs.io/en/latest/
Project-URL: Source, https://github.com/cwru-sdle/FAIRLinked
Project-URL: Tracker, https://github.com/cwru-sdle/FAIRLinked/issues
Project-URL: Homepage, https://cwrusdle.bitbucket.io/
Classifier: Development Status :: 4 - Beta
Classifier: License :: OSI Approved :: BSD License
Classifier: Programming Language :: Python :: 3
Classifier: Programming Language :: Python :: 3.9
Classifier: Intended Audience :: Science/Research
Classifier: Topic :: Scientific/Engineering :: Information Analysis
Requires-Python: >=3.9.18
License-File: LICENSE.txt
Requires-Dist: rdflib>=7.0.0
Requires-Dist: typing-extensions>=4.0.0
Requires-Dist: pyarrow>=11.0.0
Requires-Dist: openpyxl>=3.0.0
Requires-Dist: pandas>=1.0.0
Requires-Dist: cemento>=0.6.1
Requires-Dist: fuzzysearch>=0.8.0
Requires-Dist: tqdm>=4.0.0
Requires-Dist: pyld>=2.0.3
Provides-Extra: dev
Requires-Dist: pytest; extra == "dev"
Requires-Dist: pytest-cov; extra == "dev"
Dynamic: author
Dynamic: author-email
Dynamic: classifier
Dynamic: description
Dynamic: description-content-type
Dynamic: license
Dynamic: license-file
Dynamic: project-url
Dynamic: provides-extra
Dynamic: requires-dist
Dynamic: requires-python
Dynamic: summary
